sqlalchemy_access/__init__.py
sqlalchemy_access/base.py
sqlalchemy_access/pyodbc.py
sqlalchemy_access/requirements.py
sqlalchemy_access-2.0.3.dist-info/AUTHORS
sqlalchemy_access-2.0.3.dist-info/LICENSE
sqlalchemy_access-2.0.3.dist-info/METADATA
sqlalchemy_access-2.0.3.dist-info/WHEEL
sqlalchemy_access-2.0.3.dist-info/entry_points.txt
sqlalchemy_access-2.0.3.dist-info/top_level.txt
sqlalchemy_access-2.0.3.dist-info/RECORD
