Metadata-Version: 2.1
Name: sqlalchemy-access
Version: 2.0.3
Summary: MS Access for SQLAlchemy
Home-page: https://github.com/gordthompson/sqlalchemy-access
Author: Gord Thompson
Author-email: gord@gordthompson.com
License: MIT
Project-URL: Documentation, https://github.com/gordthompson/sqlalchemy-access/wiki
Project-URL: Source, https://github.com/gordthompson/sqlalchemy-access
Project-URL: Tracker, https://github.com/gordthompson/sqlalchemy-access/issues
Keywords: SQLAlchemy Microsoft Access
Classifier: Development Status :: 5 - Production/Stable
Classifier: Intended Audience :: Developers
Classifier: License :: OSI Approved :: MIT License
Classifier: Programming Language :: Python
Classifier: Programming Language :: Python :: 3
Classifier: Programming Language :: Python :: Implementation :: CPython
Classifier: Topic :: Database :: Front-Ends
Classifier: Operating System :: Microsoft :: Windows
License-File: LICENSE
License-File: AUTHORS
Requires-Dist: SQLAlchemy>=2.0.0
Requires-Dist: pyodbc>=4.0.27
Requires-Dist: pywin32
